pyntegrant/__init__.py
pyntegrant/helpers.py
pyntegrant/initializer.py
pyntegrant/loaders.py
pyntegrant/map.py
pyntegrant/py.typed
pyntegrant/system.py
pyntegrant-0.2.1.dist-info/LICENSE
pyntegrant-0.2.1.dist-info/WHEEL
pyntegrant-0.2.1.dist-info/METADATA
pyntegrant-0.2.1.dist-info/RECORD
