Metadata-Version: 2.1
Name: pyntegrant
Version: 0.2.1
Summary: A system assembly framework based on Integrant
Home-page: https://github.com/vputz/pyntegrant
License: Apache-2.0
Author: Vic Putz
Author-email: vbputz@gmail.com
Requires-Python: >=3.9,<4.0
Classifier: License :: OSI Approved :: Apache Software License
Classifier: Programming Language :: Python :: 3
Classifier: Programming Language :: Python :: 3.9
Classifier: Programming Language :: Python :: 3.10
Classifier: Topic :: Software Development :: Libraries :: Python Modules
Requires-Dist: icontract (>=2.6.0,<3.0.0)
Requires-Dist: networkx (>=2.6,<3.0)
Requires-Dist: pyrsistent (>=0.18.0,<0.19.0)
Requires-Dist: toml (>=0.10.2,<0.11.0)
Requires-Dist: toolz (>=0.11.2,<0.12.0)
